pytest_html_plus/__init__.py
pytest_html_plus/compute_filter_counts.py
pytest_html_plus/compute_report_metadata.py
pytest_html_plus/extract_link.py
pytest_html_plus/generate_html_report.py
pytest_html_plus/json_merge.py
pytest_html_plus/json_to_xml_converter.py
pytest_html_plus/plugin.py
pytest_html_plus/resolver_driver.py
pytest_html_plus/send_email_report.py
pytest_html_plus/utils.py
pytest_html_plus-0.4.9.dist-info/LICENSE
pytest_html_plus-0.4.9.dist-info/METADATA
pytest_html_plus-0.4.9.dist-info/WHEEL
pytest_html_plus-0.4.9.dist-info/entry_points.txt
pytest_html_plus-0.4.9.dist-info/RECORD
