Metadata-Version: 2.3
Name: pytest-html-plus
Version: 0.4.9
Summary: Generate Actionable, automatic screenshots, unified Mobile friendly Pytest HTML report in less than 3 seconds — no hooks, merge plugins, no config, xdist-ready.
License: MIT
Keywords: pytest,pytest-html-plus,pytest-plugin,html-test-report,beautiful-test-report,shareable-test-results,test-report,test-results,unit-test-report,functional-test-report,test-summary,reporting,python-testing,automated-testing,test-runner,report-generator,continuous-integration,ci-cd,github-actions,jenkins,pytest-html,pytest-report
Author: reporterplus
Requires-Python: >=3.9,<4.0
Classifier: License :: OSI Approved :: MIT License
Classifier: Programming Language :: Python :: 3
Classifier: Programming Language :: Python :: 3.9
Classifier: Programming Language :: Python :: 3.10
Classifier: Programming Language :: Python :: 3.11
Classifier: Programming Language :: Python :: 3.12
Classifier: Programming Language :: Python :: 3.13
Requires-Dist: keyring (>=25.6.0,<26.0.0)
Requires-Dist: yagmail (>=0.15.293,<0.16.0)
Project-URL: Homepage, https://github.com/reporterplus/pytest-html-plus
Project-URL: Source, https://github.com/reporterplus/pytest-html-plus
Project-URL: Tracker, https://github.com/reporterplus/pytest-html-plus/issues
